qat/lang/__init__.pyd
qat/lang/decorator.pyd
qat/lang/version.pyd
qat/lang/AQASM/__init__.pyd
qat/lang/AQASM/aqasm_util.pyd
qat/lang/AQASM/arithmetic.pyd
qat/lang/AQASM/bits.pyd
qat/lang/AQASM/classarith.pyd
qat/lang/AQASM/gates.pyd
qat/lang/AQASM/math_util.pyd
qat/lang/AQASM/misc.pyd
qat/lang/AQASM/operations.pyd
qat/lang/AQASM/oracle_synthesis.pyd
qat/lang/AQASM/oracles.pyd
qat/lang/AQASM/program.pyd
qat/lang/AQASM/qbool.pyd
qat/lang/AQASM/qboso.pyd
qat/lang/AQASM/qftarith.pyd
qat/lang/AQASM/qint.pyd
qat/lang/AQASM/qtype_util.pyd
qat/lang/AQASM/resources.pyd
qat/lang/AQASM/routines.pyd
qat/lang/AQASM/scope.pyd
qat/lang/AQASM/util.pyd
qat/lang/algorithms/__init__.pyd
qat/lang/algorithms/amplification.pyd
qat/lang/algorithms/estimation.pyd
qat/lang/linking/__init__.pyd
qat/lang/linking/linker.pyd
qat/lang/linking/plugin.pyd
qat/lang/linking/util.pyd
qat/lang/maths/__init__.pyd
qat/lang/maths/gradient.pyd
qat/lang/models/__init__.pyd
qat/lang/models/kp_tree.pyd
qat/lang/models/routines.pyd
qat/lang/parser/__init__.pyd
qat/lang/parser/aqasm_lexer.pyd
qat/lang/parser/aqasm_parser.pyd
qat/lang/parser/compiler.pyd
qat/lang/parser/gates_ast.pyd
qat/lang/qpus/__init__.pyd
qat/lang/qpus/classical_qpu.pyd
qat/plugins/causal_cone_plugin.pyd
qat/plugins/circuit_generation.pyd
qat/plugins/inliner_hook.pyd
qat/plugins/observable_clifford.pyd
qat/plugins/observable_splitter.pyd
qat/qpus/hook_lang.pyd
qat_lang-3.3.0.data/scripts/aqasm2circ
qat_lang-3.3.0.data/scripts/circ2aqasm
qat_lang-3.3.0.dist-info/licenses/LICENSE.txt
qat_lang-3.3.0.dist-info/METADATA
qat_lang-3.3.0.dist-info/WHEEL
qat_lang-3.3.0.dist-info/top_level.txt
qat_lang-3.3.0.dist-info/RECORD
